hyteratak/__init__.py
hyteratak/__main__.py
hyteratak/cli/__init__.py
hyteratak/cli/hytera_tak_bridge.py
hyteratak/cli/hyteratak_start.py
hyteratak/kaitai/__init__.py
hyteratak/kaitai/data_delivery_states.py
hyteratak/kaitai/data_transmit_protocol.py
hyteratak/kaitai/datetimestring.py
hyteratak/kaitai/gpsdata.py
hyteratak/kaitai/hytera_dmr_application_protocol.py
hyteratak/kaitai/hytera_simple_transport_reliability_protocol.py
hyteratak/kaitai/intervalstring.py
hyteratak/kaitai/location_protocol.py
hyteratak/kaitai/radio_control_protocol.py
hyteratak/kaitai/radio_ip.py
hyteratak/kaitai/radio_registration_service.py
hyteratak/kaitai/telemetry_protocol.py
hyteratak/kaitai/text_message_protocol.py
hyteratak/lib/__init__.py
hyteratak/lib/custom_bridge_datagram_protocol.py
hyteratak/lib/hytera_protocols.py
hyteratak/lib/hytera_tak_translator.py
hyteratak/lib/logging_trait.py
hyteratak/lib/settings.py
hyteratak-1.1.1.dist-info/LICENSE
hyteratak-1.1.1.dist-info/METADATA
hyteratak-1.1.1.dist-info/NOTICE
hyteratak-1.1.1.dist-info/WHEEL
hyteratak-1.1.1.dist-info/entry_points.txt
hyteratak-1.1.1.dist-info/top_level.txt
hyteratak-1.1.1.dist-info/RECORD
