Metadata-Version: 2.1
Name: hyteratak
Version: 1.1.1
Summary: Hytera to Cursor-On-Target Gateway
Home-page: https://github.com/kortel-systems/hyteratak
Author: Kortel
Author-email: hytera@kortel.systems
Project-URL: Bug Tracker, https://github.com/kortel-systems/hyteratak/issues
Keywords: Hytera,repeater,dmr,Cursor on Target,ATAK,TAK,CoT
Classifier: Programming Language :: Python :: 3.7
Classifier: License :: OSI Approved :: Apache Software License
Classifier: Development Status :: 3 - Alpha
Classifier: Environment :: Console
Classifier: Topic :: Communications :: Ham Radio
Classifier: Operating System :: POSIX :: Linux
Classifier: Typing :: Typed
Classifier: Intended Audience :: Telecommunications Industry
Classifier: Natural Language :: English
Requires-Python: ~=3.7
License-File: LICENSE
License-File: NOTICE
Requires-Dist: configparser (>=5.0.1)
Requires-Dist: kaitaistruct (>=0.9)
Requires-Dist: asyncio (>=3.4.3)
Requires-Dist: pytak (==3.5.2)
